{
 "cells": [
  {
   "cell_type": "markdown",
   "metadata": {},
   "source": ["# 02 — Qubit Calibration\n", "Full qubit characterization: ge and ef transitions.\n", "Run after cooldown or when qubit params drift significantly."]
  },
  {
   "cell_type": "code",
   "execution_count": null,
   "metadata": {},
   "outputs": [],
   "source": [
    "%load_ext autoreload\n",
    "%autoreload 2\n",
    "\n",
    "import sys\n",
    "sys.path.insert(0, 'C:\\\\Users\\\\Administrator\\\\Documents\\\\multimode_expts_tprocv2')\n",
    "\n",
    "import numpy as np\n",
    "import matplotlib.pyplot as plt\n",
    "from meas_utils import MultimodeStation\n",
    "from calibration_helpers import (\n",
    "    init_helpers,\n",
    "    do_pulse_probe_spec, update_pulse_probe_ge, update_pulse_probe_ef,\n",
    "    do_t2_ramsey, update_t2_ramsey_ge, update_t2_ramsey_ef,\n",
    "    do_rabi, update_amplitude_rabi_ge, update_amplitude_rabi_ef,\n",
    "    do_t1,\n",
    ")\n",
    "\n",
    "station = MultimodeStation(\n",
    "    experiment_name  = '2600403_lmm',\n",
    "    hardware_config  = 'hardware_config_20260111.yml',\n",
    ")\n",
    "init_helpers(station)\n",
    "config_thisrun = station.config_thisrun\n",
    "cfg_dict       = station.cfg_dict\n",
    "meas           = station.meas\n",
    "print('Station ready.')"
   ]
  },
  {
   "cell_type": "markdown",
   "metadata": {},
   "source": ["## Qubit GE"]
  },
  {
   "cell_type": "code",
   "execution_count": null,
   "metadata": {},
   "outputs": [],
   "source": [
    "qspec_ge = do_pulse_probe_spec(\n",
    "    config_thisrun      = config_thisrun,\n",
    "    center              = config_thisrun.device.qubit.f_ge,\n",
    "    span                = 20,\n",
    "    expts               = 300,\n",
    "    reps                = 300,\n",
    "    rounds              = 1,\n",
    "    pulse_e             = False,\n",
    "    prepulse            = {},\n",
    "    postpulse           = {},\n",
    "    sweep_other_param   = None,\n",
    "    probe_pulse_param   = {\n",
    "        'gain':           0.05,\n",
    "        'length':         0.8,\n",
    "        'freq':           None,\n",
    "        'chan':           config_thisrun.hw.soc.dacs.qubit.ch,\n",
    "        'sigma':          0,\n",
    "        'sigma_inc':      0,\n",
    "        'ramp_sigma':     None,\n",
    "        'ramp_sigma_inc': None,\n",
    "        'phase':          0,\n",
    "        'type':           'const',\n",
    "    },\n",
    "    analyze_and_display = True,\n",
    ")"
   ]
  },
  {
   "cell_type": "code",
   "execution_count": null,
   "metadata": {},
   "outputs": [],
   "source": [
    "update_pulse_probe_ge(\n",
    "    qspec          = qspec_ge,\n",
    "    config_thisrun = config_thisrun,\n",
    ")"
   ]
  },
  {
   "cell_type": "code",
   "execution_count": null,
   "metadata": {},
   "outputs": [],
   "source": [
    "t2_ge = do_t2_ramsey(\n",
    "    config_thisrun      = config_thisrun,\n",
    "    cfg_dict            = cfg_dict,\n",
    "    prepulse            = {},\n",
    "    postpulse           = {},\n",
    "    start               = 0.01,\n",
    "    step_size           = 0.02,\n",
    "    expts               = 500,\n",
    "    ramsey_freq         = 0.6,\n",
    "    reps                = 500,\n",
    "    rounds              = 1,\n",
    "    sigma               = config_thisrun.device.qubit.pulses.hpi_ge.sigma,\n",
    "    sigma_inc           = 4,\n",
    "    freq                = config_thisrun.device.qubit.f_ge,\n",
    "    gain                = config_thisrun.device.qubit.pulses.hpi_ge.gain,\n",
    "    pulse_type          = 'gauss',\n",
    "    analyze_and_display = False,\n",
    "    sweep_other_param   = {},\n",
    ")\n",
    "t2_ge_fit = meas.RamseyFitting(t2_ge.data, config=t2_ge.cfg)\n",
    "t2_ge_fit.analyze(fitparams=[None, 0.5, None, None, None, None])\n",
    "t2_ge_fit.display(title_str='T2_ge')"
   ]
  },
  {
   "cell_type": "code",
   "execution_count": null,
   "metadata": {},
   "outputs": [],
   "source": [
    "update_t2_ramsey_ge(\n",
    "    t2ramsey       = t2_ge_fit,\n",
    "    config_thisrun = config_thisrun,\n",
    ")"
   ]
  },
  {
   "cell_type": "code",
   "execution_count": null,
   "metadata": {},
   "outputs": [],
   "source": [
    "rabi_ge = do_rabi(\n",
    "    config_thisrun      = config_thisrun,\n",
    "    cfg_dict            = cfg_dict,\n",
    "    start               = 0.001,\n",
    "    expts               = 300,\n",
    "    reps                = 500,\n",
    "    rounds              = 1,\n",
    "    pulse_type          = 'gauss',\n",
    "    sweep               = 'amp',\n",
    "    chan                = config_thisrun.hw.soc.dacs.qubit.ch,\n",
    "    freq                = config_thisrun.device.qubit.f_ge,\n",
    "    gain                = 0.0,\n",
    "    sigma               = 0.03,\n",
    "    sigma_inc           = 4,\n",
    "    length              = 0.0,\n",
    "    ramp_sigma          = 0.02,\n",
    "    ramp_sigma_inc      = 0.0,\n",
    "    n_pulses            = 1,\n",
    "    prepulse            = {},\n",
    "    postpulse           = {},\n",
    "    max_gain            = 0.8,\n",
    "    max_length          = 10.0,\n",
    "    sweep_other_param   = {},\n",
    ")\n",
    "rabi_ge.analyze()\n",
    "rabi_ge.display(title_str='Amplitude Rabi ge')"
   ]
  },
  {
   "cell_type": "code",
   "execution_count": null,
   "metadata": {},
   "outputs": [],
   "source": [
    "update_amplitude_rabi_ge(\n",
    "    amprabi        = rabi_ge,\n",
    "    config_thisrun = config_thisrun,\n",
    ")"
   ]
  },
  {
   "cell_type": "code",
   "execution_count": null,
   "metadata": {},
   "outputs": [],
   "source": [
    "# T2 Ramsey ge post-rabi fine tune\n",
    "t2_ge_2 = do_t2_ramsey(\n",
    "    config_thisrun      = config_thisrun,\n",
    "    cfg_dict            = cfg_dict,\n",
    "    prepulse            = {},\n",
    "    postpulse           = {},\n",
    "    start               = 0.01,\n",
    "    step_size           = 0.02,\n",
    "    expts               = 500,\n",
    "    ramsey_freq         = 0.6,\n",
    "    reps                = 500,\n",
    "    rounds              = 1,\n",
    "    sigma               = config_thisrun.device.qubit.pulses.hpi_ge.sigma,\n",
    "    sigma_inc           = 4,\n",
    "    freq                = config_thisrun.device.qubit.f_ge,\n",
    "    gain                = config_thisrun.device.qubit.pulses.hpi_ge.gain,\n",
    "    pulse_type          = 'gauss',\n",
    "    analyze_and_display = False,\n",
    "    sweep_other_param   = {},\n",
    ")\n",
    "t2_ge_fit_2 = meas.RamseyFitting(t2_ge_2.data, config=t2_ge_2.cfg)\n",
    "t2_ge_fit_2.analyze(fitparams=[None, 0.5, None, None, None, None])\n",
    "t2_ge_fit_2.display(title_str='T2_ge post-rabi')\n",
    "update_t2_ramsey_ge(\n",
    "    t2ramsey       = t2_ge_fit_2,\n",
    "    config_thisrun = config_thisrun,\n",
    ")"
   ]
  },
  {
   "cell_type": "code",
   "execution_count": null,
   "metadata": {},
   "outputs": [],
   "source": [
    "t1_ge = do_t1(\n",
    "    config_thisrun      = config_thisrun,\n",
    "    cfg_dict            = cfg_dict,\n",
    "    prepulse            = {},\n",
    "    start               = 0.01,\n",
    "    step_size           = 0.5,\n",
    "    expts               = 200,\n",
    "    reps                = 300,\n",
    "    rounds              = 1,\n",
    "    sigma               = config_thisrun.device.qubit.pulses.pi_ge.sigma,\n",
    "    sigma_inc           = 4,\n",
    "    freq                = config_thisrun.device.qubit.f_ge,\n",
    "    gain                = config_thisrun.device.qubit.pulses.pi_ge.gain,\n",
    "    pulse_type          = 'gauss',\n",
    "    analyze_and_display = True,\n",
    ")"
   ]
  },
  {
   "cell_type": "markdown",
   "metadata": {},
   "source": ["## Qubit EF"]
  },
  {
   "cell_type": "code",
   "execution_count": null,
   "metadata": {},
   "outputs": [],
   "source": [
    "qspec_ef = do_pulse_probe_spec(\n",
    "    config_thisrun      = config_thisrun,\n",
    "    center              = config_thisrun.device.qubit.f_ef,\n",
    "    span                = 50,\n",
    "    expts               = 300,\n",
    "    reps                = 100,\n",
    "    rounds              = 1,\n",
    "    pulse_e             = False,\n",
    "    prepulse            = {'pi_qubit_ge': {}},\n",
    "    postpulse           = {'pi_qubit_ge': {}},\n",
    "    sweep_other_param   = None,\n",
    "    probe_pulse_param   = {\n",
    "        'gain':           0.05,\n",
    "        'length':         0.35,\n",
    "        'freq':           None,\n",
    "        'chan':           config_thisrun.hw.soc.dacs.qubit.ch,\n",
    "        'sigma':          0,\n",
    "        'sigma_inc':      0,\n",
    "        'ramp_sigma':     None,\n",
    "        'ramp_sigma_inc': None,\n",
    "        'phase':          0,\n",
    "        'type':           'const',\n",
    "    },\n",
    "    analyze_and_display = True,\n",
    ")"
   ]
  },
  {
   "cell_type": "code",
   "execution_count": null,
   "metadata": {},
   "outputs": [],
   "source": [
    "update_pulse_probe_ef(\n",
    "    qspec          = qspec_ef,\n",
    "    config_thisrun = config_thisrun,\n",
    ")"
   ]
  },
  {
   "cell_type": "code",
   "execution_count": null,
   "metadata": {},
   "outputs": [],
   "source": [
    "t2_ef = do_t2_ramsey(\n",
    "    config_thisrun      = config_thisrun,\n",
    "    cfg_dict            = cfg_dict,\n",
    "    prepulse            = {'pi_qubit_ge': {}},\n",
    "    postpulse           = {'pi_qubit_ge': {}},\n",
    "    start               = 0.01,\n",
    "    step_size           = 0.02,\n",
    "    expts               = 500,\n",
    "    ramsey_freq         = 0.6,\n",
    "    reps                = 300,\n",
    "    rounds              = 1,\n",
    "    sigma               = config_thisrun.device.qubit.pulses.hpi_ef.sigma,\n",
    "    sigma_inc           = 4,\n",
    "    freq                = config_thisrun.device.qubit.f_ef,\n",
    "    gain                = config_thisrun.device.qubit.pulses.hpi_ef.gain,\n",
    "    pulse_type          = 'gauss',\n",
    "    analyze_and_display = False,\n",
    "    sweep_other_param   = {},\n",
    ")\n",
    "t2_ef_fit = meas.RamseyFitting(t2_ef.data, config=t2_ef.cfg)\n",
    "t2_ef_fit.analyze(fitparams=[None, 0.5, None, None, None, None])\n",
    "t2_ef_fit.display(title_str='T2_ef')"
   ]
  },
  {
   "cell_type": "code",
   "execution_count": null,
   "metadata": {},
   "outputs": [],
   "source": [
    "update_t2_ramsey_ef(\n",
    "    t2ramsey       = t2_ef_fit,\n",
    "    config_thisrun = config_thisrun,\n",
    ")"
   ]
  },
  {
   "cell_type": "code",
   "execution_count": null,
   "metadata": {},
   "outputs": [],
   "source": [
    "rabi_ef = do_rabi(\n",
    "    config_thisrun      = config_thisrun,\n",
    "    cfg_dict            = cfg_dict,\n",
    "    start               = 0.001,\n",
    "    expts               = 151,\n",
    "    reps                = 100,\n",
    "    rounds              = 1,\n",
    "    pulse_type          = 'gauss',\n",
    "    sweep               = 'amp',\n",
    "    chan                = config_thisrun.hw.soc.dacs.qubit.ch,\n",
    "    freq                = config_thisrun.device.qubit.f_ef,\n",
    "    gain                = 0.0,\n",
    "    sigma               = 0.03,\n",
    "    sigma_inc           = 4,\n",
    "    length              = 0.0,\n",
    "    ramp_sigma          = 0.02,\n",
    "    ramp_sigma_inc      = 0.0,\n",
    "    n_pulses            = 1,\n",
    "    prepulse            = {'pi_qubit_ge': {}},\n",
    "    postpulse           = {'pi_qubit_ge': {}},\n",
    "    max_gain            = 1.0,\n",
    "    max_length          = 10.0,\n",
    "    sweep_other_param   = {},\n",
    ")\n",
    "rabi_ef.analyze()\n",
    "rabi_ef.display(title_str='Amplitude Rabi ef')"
   ]
  },
  {
   "cell_type": "code",
   "execution_count": null,
   "metadata": {},
   "outputs": [],
   "source": [
    "update_amplitude_rabi_ef(\n",
    "    amprabi        = rabi_ef,\n",
    "    config_thisrun = config_thisrun,\n",
    ")"
   ]
  },
  {
   "cell_type": "code",
   "execution_count": null,
   "metadata": {},
   "outputs": [],
   "source": [
    "# T2 Ramsey ef post-rabi fine tune\n",
    "t2_ef_2 = do_t2_ramsey(\n",
    "    config_thisrun      = config_thisrun,\n",
    "    cfg_dict            = cfg_dict,\n",
    "    prepulse            = {'pi_qubit_ge': {}},\n",
    "    postpulse           = {'pi_qubit_ge': {}},\n",
    "    start               = 0.01,\n",
    "    step_size           = 0.02,\n",
    "    expts               = 500,\n",
    "    ramsey_freq         = 0.6,\n",
    "    reps                = 300,\n",
    "    rounds              = 1,\n",
    "    sigma               = config_thisrun.device.qubit.pulses.hpi_ef.sigma,\n",
    "    sigma_inc           = 4,\n",
    "    freq                = config_thisrun.device.qubit.f_ef,\n",
    "    gain                = config_thisrun.device.qubit.pulses.hpi_ef.gain,\n",
    "    pulse_type          = 'gauss',\n",
    "    analyze_and_display = False,\n",
    "    sweep_other_param   = {},\n",
    ")\n",
    "t2_ef_fit_2 = meas.RamseyFitting(t2_ef_2.data, config=t2_ef_2.cfg)\n",
    "t2_ef_fit_2.analyze(fitparams=[None, 0.5, None, None, None, None])\n",
    "t2_ef_fit_2.display(title_str='T2_ef post-rabi')\n",
    "update_t2_ramsey_ef(\n",
    "    t2ramsey       = t2_ef_fit_2,\n",
    "    config_thisrun = config_thisrun,\n",
    ")"
   ]
  },
  {
   "cell_type": "code",
   "execution_count": null,
   "metadata": {},
   "outputs": [],
   "source": [
    "t1_ef = do_t1(\n",
    "    config_thisrun      = config_thisrun,\n",
    "    cfg_dict            = cfg_dict,\n",
    "    prepulse            = {'pi_qubit_ge': {}},\n",
    "    start               = 0.01,\n",
    "    step_size           = 0.5,\n",
    "    expts               = 200,\n",
    "    reps                = 300,\n",
    "    rounds              = 1,\n",
    "    sigma               = config_thisrun.device.qubit.pulses.pi_ef.sigma,\n",
    "    sigma_inc           = 4,\n",
    "    freq                = config_thisrun.device.qubit.f_ef,\n",
    "    gain                = config_thisrun.device.qubit.pulses.pi_ef.gain,\n",
    "    pulse_type          = 'gauss',\n",
    "    analyze_and_display = True,\n",
    ")"
   ]
  },
  {
   "cell_type": "code",
   "execution_count": null,
   "metadata": {},
   "outputs": [],
   "source": [
    "station.handle_config_update(write_to_file=True)\n",
    "print('Config saved.')"
   ]
  }
 ],
 "metadata": {
  "kernelspec": {
   "display_name": "mm313",
   "language": "python",
   "name": "python3"
  },
  "language_info": {
   "name": "python",
   "version": "3.13.9"
  }
 },
 "nbformat": 4,
 "nbformat_minor": 4
}
